sum_sum/__init__.py
sum_sum/main.py
sum_sum-0.1.0.1.dist-info/METADATA
sum_sum-0.1.0.1.dist-info/WHEEL
sum_sum-0.1.0.1.dist-info/entry_points.txt
sum_sum-0.1.0.1.dist-info/RECORD
